dfv/__init__.py
dfv/element.py
dfv/element_tests.py
dfv/form.py
dfv/form_tests.py
dfv/htmx.py
dfv/inject_params.py
dfv/inject_params_test.py
dfv/middleware.py
dfv/response_handler.py
dfv/response_handler_tests.py
dfv/static/dfv.js
dfv/static/dfv_swap_merge.js
dfv/swap_oob_tests.py
dfv/templates/dfv/tests/TemplateResponse.html
dfv/templatetags/__init__.py
dfv/templatetags/dfv.py
dfv/testutils.py
dfv/utils.py
dfv/view.py
dfv/view_stack.py
dfv/view_tests.py
dfv-0.47.0.dist-info/METADATA
dfv-0.47.0.dist-info/WHEEL
dfv-0.47.0.dist-info/RECORD
